dprojects_xmenu/__init__.py
dprojects_xmenu/module.py
dprojects_xmenu-0.0.3.dist-info/LICENSE
dprojects_xmenu-0.0.3.dist-info/METADATA
dprojects_xmenu-0.0.3.dist-info/WHEEL
dprojects_xmenu-0.0.3.dist-info/top_level.txt
dprojects_xmenu-0.0.3.dist-info/RECORD
